py_nf/__init__.py
py_nf/py_nf.py
py_nf/utils.py
py_nf-0.1.0.dist-info/LICENSE
py_nf-0.1.0.dist-info/METADATA
py_nf-0.1.0.dist-info/WHEEL
py_nf-0.1.0.dist-info/top_level.txt
py_nf-0.1.0.dist-info/RECORD
