Metadata-Version: 2.1
Name: py-nf
Version: 0.1.0
Summary: Execute batches of jobs with nextflow
Home-page: https://github.com/kirilenkobm/py_nf
Author: Bogdan Kirilenko
Author-email: kirilenkobm@gmail.com
License: MIT
Platform: UNKNOWN
Classifier: Programming Language :: Python :: 3
Classifier: License :: OSI Approved :: MIT License
Classifier: Operating System :: POSIX
Classifier: Development Status :: 2 - Pre-Alpha
Classifier: Topic :: Scientific/Engineering :: Bio-Informatics
